pratix_nelog/__init__.py
pratix_nelog/consolidator.py
pratix_nelog/exceptions.py
pratix_nelog/parser.py
pratix_nelog/utils.py
pratix_nelog-0.2.4.dist-info/METADATA
pratix_nelog-0.2.4.dist-info/WHEEL
pratix_nelog-0.2.4.dist-info/top_level.txt
pratix_nelog-0.2.4.dist-info/RECORD
