Metadata-Version: 2.1
Name: pratix-nelog
Version: 0.2.4
Summary: A library to analyze network logs in multiple formats and consolidate them into JSON.
Home-page: https://github.com/pratiklahudkar/pratix-nelog
Author: Pratik
Author-email: pratik.lahudkar@gmail.com
Classifier: Programming Language :: Python :: 3
Classifier: License :: OSI Approved :: MIT License
Classifier: Operating System :: OS Independent
Requires-Python: >=3.6
